emcli/__init__.py
emcli/__main__.py
emcli/commands/__init__.py
emcli/commands/asg.py
emcli/commands/base.py
emcli/commands/cycle.py
emcli/commands/deploy.py
emcli/commands/instance.py
emcli/commands/patch.py
emcli/commands/publish.py
emcli/commands/service.py
emcli/commands/spinner.py
emcli/commands/toggle.py
emcli/commands/user_confirmation.py
emcli/commands/verify.py
emcli/commands/patching/__init__.py
emcli/commands/patching/patch_file.py
emcli/commands/patching/patch_operation.py
emcli/commands/patching/patch_process.py
emcli/commands/patching/patch_progress.py
emcli/commands/patching/patch_states.py
emcli/commands/patching/patch_table.py
emcli/commands/patching/validate.py
emcli/commands/utils/__init__.py
emcli/commands/utils/asg_health.py
emcli/commands/utils/file_utils.py
envmgr_cli-1.13.2.dist-info/LICENSE.txt
envmgr_cli-1.13.2.dist-info/METADATA
envmgr_cli-1.13.2.dist-info/NOTICE.txt
envmgr_cli-1.13.2.dist-info/WHEEL
envmgr_cli-1.13.2.dist-info/entry_points.txt
envmgr_cli-1.13.2.dist-info/top_level.txt
envmgr_cli-1.13.2.dist-info/RECORD
