Metadata-Version: 2.1
Name: envmgr-cli
Version: 1.13.2
Summary: Environment Manager CLI tool.
Home-page: https://github.com/trainline/envmgr-cli
Author: Trainline Platform Development
Author-email: platform.development@thetrainline.com
License: Apache 2.0
Platform: UNKNOWN
Requires-Dist: docopt (~=0.6.2)
Requires-Dist: simplejson (~=3.11.1)
Requires-Dist: tabulate (~=0.7.7)
Requires-Dist: future (~=0.16.0)
Requires-Dist: semver (~=2.7.7)
Requires-Dist: appdirs (~=1.4.3)
Requires-Dist: progressbar2 (~=3.30.2)
Requires-Dist: envmgr-lib (==0.3.0)
